[
    {
        "first_name": "Paweł",
        "last_name": "Nowak",
        "pesel": "03759300121",
        "grades": [
            {
                "value": 5.0,
                "form": "Test",
                "notes": "",
                "date": "2025-06-02"
            },
            {
                "value": 3.0,
                "form": "Homework",
                "notes": "Not done properly",
                "date": "2025-06-02"
            }
        ],
        "group": "Group 1",
        "attendance_records": [
            {
                "date": "2025-05-21",
                "status": "absent"
            },
            {
                "date": "2025-05-20",
                "status": "present"
            },
            {
                "date": "2025-05-19",
                "status": "absent"
            },
            {
                "date": "2025-05-23",
                "status": "excused"
            },
            {
                "date": "2025-05-25",
                "status": "present"
            },
            {
                "date": "2025-05-24",
                "status": "present"
            },
            {
                "date": "2025-06-01",
                "status": "present"
            },
            {
                "date": "2025-05-31",
                "status": "present"
            },
            {
                "date": "2025-06-02",
                "status": "late"
            }
        ]
    },
    {
        "first_name": "Kasia",
        "last_name": "Paluch",
        "pesel": "32453434253",
        "grades": [
            {
                "value": 2.0,
                "form": "Test",
                "notes": "",
                "date": "2025-05-24"
            }
        ],
        "group": "Group 2",
        "attendance_records": [
            {
                "date": "2025-05-21",
                "status": "absent"
            },
            {
                "date": "2025-05-23",
                "status": "present"
            },
            {
                "date": "2025-05-22",
                "status": "late"
            },
            {
                "date": "2025-05-24",
                "status": "present"
            },
            {
                "date": "2025-05-25",
                "status": "present"
            }
        ]
    },
    {
        "first_name": "Tomasz",
        "last_name": "Kot",
        "pesel": "32111153453",
        "grades": [
            {
                "value": 3.5,
                "form": "Test",
                "notes": "",
                "date": "2025-06-01"
            }
        ],
        "group": "Group 2",
        "attendance_records": [
            {
                "date": "2025-05-22",
                "status": "absent"
            },
            {
                "date": "2025-05-21",
                "status": "absent"
            },
            {
                "date": "2025-05-23",
                "status": "present"
            },
            {
                "date": "2025-05-24",
                "status": "absent"
            },
            {
                "date": "2025-05-25",
                "status": "late"
            }
        ]
    },
    {
        "first_name": "Anna",
        "last_name": "Zalewska",
        "pesel": "12345678901",
        "grades": [
            {
                "value": 4.5,
                "form": "Exam",
                "notes": "Good work",
                "date": "2025-05-21"
            }
        ],
        "group": "Group 1",
        "attendance_records": [
            {
                "date": "2025-05-25",
                "status": "absent"
            },
            {
                "date": "2025-05-24",
                "status": "present"
            },
            {
                "date": "2025-06-01",
                "status": "excused"
            },
            {
                "date": "2025-05-31",
                "status": "excused"
            },
            {
                "date": "2025-06-02",
                "status": "late"
            }
        ]
    },
    {
        "first_name": "Marek",
        "last_name": "Kowalski",
        "pesel": "11122233344",
        "grades": [
            {
                "value": 3.0,
                "form": "Quiz",
                "notes": "Could be better",
                "date": "2025-05-20"
            },
            {
                "value": 4.0,
                "form": "Homework",
                "notes": "",
                "date": "2025-05-19"
            }
        ],
        "group": "Group 2",
        "attendance_records": [
            {
                "date": "2025-05-20",
                "status": "present"
            },
            {
                "date": "2025-05-19",
                "status": "late"
            },
            {
                "date": "2025-05-22",
                "status": "present"
            },
            {
                "date": "2025-05-23",
                "status": "present"
            },
            {
                "date": "2025-05-24",
                "status": "excused"
            },
            {
                "date": "2025-05-25",
                "status": "excused"
            }
        ]
    },
    {
        "first_name": "Ewa",
        "last_name": "Nowicka",
        "pesel": "55566677788",
        "grades": [
            {
                "value": 4.0,
                "form": "Test",
                "notes": "Nice answers",
                "date": "2025-05-22"
            }
        ],
        "group": "Group 3",
        "attendance_records": [
            {
                "date": "2025-05-21",
                "status": "present"
            },
            {
                "date": "2025-05-22",
                "status": "present"
            },
            {
                "date": "2025-05-23",
                "status": "present"
            }
        ]
    },
    {
        "first_name": "Paula",
        "last_name": "Lewandowska",
        "pesel": "99887766554",
        "grades": [
            {
                "value": 5.0,
                "form": "Exam",
                "notes": "Excellent",
                "date": "2025-06-02"
            }
        ],
        "group": "Group 1",
        "attendance_records": [
            {
                "date": "2025-05-20",
                "status": "present"
            },
            {
                "date": "2025-05-21",
                "status": "present"
            },
            {
                "date": "2025-05-22",
                "status": "present"
            },
            {
                "date": "2025-05-24",
                "status": "absent"
            },
            {
                "date": "2025-06-01",
                "status": "late"
            },
            {
                "date": "2025-05-31",
                "status": "present"
            }
        ]
    },
    {
        "first_name": "Łukasz",
        "last_name": "Wiśniewski",
        "pesel": "44455566677",
        "grades": [
            {
                "value": 2.5,
                "form": "Quiz",
                "notes": "Needs improvement",
                "date": "2025-05-23"
            }
        ],
        "group": "Group 2",
        "attendance_records": [
            {
                "date": "2025-05-23",
                "status": "present"
            },
            {
                "date": "2025-05-24",
                "status": "absent"
            },
            {
                "date": "2025-05-25",
                "status": "present"
            }
        ]
    },
    {
        "first_name": "Monika",
        "last_name": "Jankowska",
        "pesel": "12312312312",
        "grades": [
            {
                "value": 3.5,
                "form": "Homework",
                "notes": "On time",
                "date": "2025-05-24"
            }
        ],
        "group": "Group 3",
        "attendance_records": [
            {
                "date": "2025-05-22",
                "status": "present"
            },
            {
                "date": "2025-05-23",
                "status": "present"
            },
            {
                "date": "2025-05-24",
                "status": "present"
            }
        ]
    },
    {
        "first_name": "Kamil",
        "last_name": "Kaczmarek",
        "pesel": "78978978978",
        "grades": [
            {
                "value": 5.0,
                "form": "Test",
                "notes": "",
                "date": "2025-06-01"
            }
        ],
        "group": "Group 1",
        "attendance_records": [
            {
                "date": "2025-05-21",
                "status": "absent"
            },
            {
                "date": "2025-05-22",
                "status": "absent"
            },
            {
                "date": "2025-05-23",
                "status": "present"
            },
            {
                "date": "2025-05-24",
                "status": "late"
            },
            {
                "date": "2025-06-01",
                "status": "excused"
            },
            {
                "date": "2025-05-31",
                "status": "excused"
            },
            {
                "date": "2025-06-02",
                "status": "excused"
            }
        ]
    }
]